rgbxmastree/__init__.py
rgbxmastree/__main__.py
rgbxmastree/cli.py
rgbxmastree/tree.py
rgbxmastree/commands/color_shuffle.py
rgbxmastree-0.2.1.dist-info/METADATA
rgbxmastree-0.2.1.dist-info/WHEEL
rgbxmastree-0.2.1.dist-info/entry_points.txt
rgbxmastree-0.2.1.dist-info/top_level.txt
rgbxmastree-0.2.1.dist-info/RECORD
