Metadata-Version: 2.2
Name: rgbxmastree
Version: 0.2.1
Summary: API and commands for interacting with the Pi Hut RGB Xmas Tree.
Requires-Python: >=3.9
Requires-Dist: gpiozero>=2.0.1
Requires-Dist: setuptools-scm>=8.1.0
Requires-Dist: typer>=0.15.1
